README.rst
setup.py
awsmfa/__init__.py
awsmfa/__main__.py
awsmfa/_version.py
awsmfa/awsmfa-basic-policies.json
awsmfa.egg-info/PKG-INFO
awsmfa.egg-info/SOURCES.txt
awsmfa.egg-info/dependency_links.txt
awsmfa.egg-info/entry_points.txt
awsmfa.egg-info/not-zip-safe
awsmfa.egg-info/requires.txt
awsmfa.egg-info/top_level.txt