Metadata-Version: 1.1
Name: awsmfa
Version: 0.2.8
Summary: Manage temporary MFA AWS credentials.
Home-page: https://github.com/dcoker/awsmfa/
Author: Doug Coker
Author-email: dcoker@gmail.com
License: https://www.apache.org/licenses/LICENSE-2.0
Platform: UNKNOWN
Classifier: Development Status :: 4 - Beta
Classifier: Environment :: Console
Classifier: Intended Audience :: Developers
Classifier: License :: OSI Approved :: Apache Software License
Classifier: Programming Language :: Python :: 2.7
Classifier: Programming Language :: Python :: 3.3
Classifier: Programming Language :: Python :: 3.4
Classifier: Programming Language :: Python :: 3.5
Classifier: Topic :: Security
